hokus_pokus/__init__.py
hokus_pokus/hokus_pokus.py
hokus_pokus-1.0.0.dist-info/LICENSE
hokus_pokus-1.0.0.dist-info/METADATA
hokus_pokus-1.0.0.dist-info/WHEEL
hokus_pokus-1.0.0.dist-info/entry_points.txt
hokus_pokus-1.0.0.dist-info/top_level.txt
hokus_pokus-1.0.0.dist-info/RECORD
