Metadata-Version: 2.1
Name: hokus-pokus
Version: 1.0.0
Summary: Your magical CLI for generating text spells and performing tasks.
Home-page: https://github.com/yourusername/hokus-pokus
Author: Your Name
Author-email: your.email@example.com
Classifier: Programming Language :: Python :: 3
Classifier: License :: OSI Approved :: MIT License
Classifier: Operating System :: OS Independent
License-File: LICENSE
Requires-Dist: transformers (>=4.0.0)
Requires-Dist: torch (>=1.8.0)
Requires-Dist: click
